hana_cloud_interface/__init__.py
hana_cloud_interface/main.py
hana_cloud_interface/py.typed
hana_cloud_interface-0.2.1.dist-info/WHEEL
hana_cloud_interface-0.2.1.dist-info/METADATA
hana_cloud_interface-0.2.1.dist-info/RECORD
