Metadata-Version: 2.3
Name: hana-cloud-interface
Version: 0.2.1
Summary: Runs a SQL command on SAP HANA Cloud using OAuth single sign on and returns a pandas or polars dataframe
Author: charlotte corpe
Author-email: charlotte corpe <charlotte.corpe@powerco.co.nz>
Requires-Dist: hdbcli
Requires-Dist: polars
Requires-Dist: pandas
Requires-Dist: hana-ml
Requires-Dist: platformdirs
Requires-Python: >=3.12
